odoo/addons/website_chartjs/README.rst
odoo/addons/website_chartjs/__init__.py
odoo/addons/website_chartjs/__manifest__.py
odoo/addons/website_chartjs/static/description/icon.png
odoo/addons/website_chartjs/static/src/css/Chart.min.css
odoo/addons/website_chartjs/static/src/js/Chart.min.js
odoo/addons/website_chartjs/views/assets.xml
odoo12_addon_website_chartjs-12.0.1.0.0.99.dev1.dist-info/METADATA
odoo12_addon_website_chartjs-12.0.1.0.0.99.dev1.dist-info/WHEEL
odoo12_addon_website_chartjs-12.0.1.0.0.99.dev1.dist-info/top_level.txt
odoo12_addon_website_chartjs-12.0.1.0.0.99.dev1.dist-info/RECORD
