Metadata-Version: 2.1
Name: odoo12-addon-website_chartjs
Version: 12.0.1.0.0.99.dev1
Summary: Add the chart js library on the website.
Home-page: https://www.sygel.es
Author: Sygel
License: AGPL-3
Classifier: Programming Language :: Python
Classifier: Framework :: Odoo
Classifier: Framework :: Odoo :: 12.0
Classifier: License :: OSI Approved :: GNU Affero General Public License v3
Requires-Python: >=3.5
Requires-Dist: odoo<12.1dev,>=12.0a
